intrinsics_dimension/__init__.py
intrinsics_dimension/intrinsics_dimension.py
intrinsics_dimension-0.1.0.dist-info/METADATA
intrinsics_dimension-0.1.0.dist-info/WHEEL
intrinsics_dimension-0.1.0.dist-info/top_level.txt
intrinsics_dimension-0.1.0.dist-info/RECORD
