Metadata-Version: 2.1
Name: intrinsics-dimension
Version: 0.1.0
Summary: Tensorized (and parallelizable) pytorch implementation of the algorithm for intrinsic dimension estimation : MLE and TWO-NN
Home-page: https://github.com/Tikquuss/intrinsics_dimension
Author: Pascal Tikeng
Author-email: pascalnotsawo@gmail.com
License: MIT
Platform: UNKNOWN
Classifier: Intended Audience :: Developers
Classifier: License :: OSI Approved :: MIT License
Classifier: Programming Language :: Python
Classifier: Programming Language :: Python :: 3
Classifier: Programming Language :: Python :: 3.6
Classifier: Programming Language :: Python :: 3.7
Classifier: Programming Language :: Python :: 3.8
Classifier: Programming Language :: Python :: 3.9
Classifier: Operating System :: OS Independent
Requires-Dist: torch
Requires-Dist: numpy
